pypavlok
