Metadata-Version: 1.0
Name: pypavlok
Version: 0.4
Summary: Unofficial Bluetooth controller for Pavlok
Home-page: http://github.com/flagist0/pypavlok
Author: Alexander Presnyakov
Author-email: flagist0@gmail.com
License: MIT
Platform: UNKNOWN
